{
  "perl": "6.d",
  "name": "DSL::Entity::English::Geographics",
  "api": "1",
  "auth": "github:antononcube",
  "version": "0.1.0",
  "description": "Grammars for geographic entities: countries, states, cities, ZIP codes, etc.",
  "authors": [
    "Anton Antonov"
  ],
  "license": "GPL-3.0-or-later",
  "provides": {
    "DSL::Entity::English::Geographics": "lib/DSL/Entity/English/Geographics.rakumod",
    "DSL::Entity::English::Geographics::ResourceAccess": "lib/DSL/Entity/English/Geographics/ResourceAccess.rakumod",
    "DSL::Entity::English::Geographics::Grammar": "lib/DSL/Entity/English/Geographics/Grammar.rakumod",
    "DSL::Entity::English::Geographics::Grammar::EntityAdjectives": "lib/DSL/Entity/English/Geographics/Grammar/EntityAdjectives.rakumod",
    "DSL::Entity::English::Geographics::Grammar::EntityNames": "lib/DSL/Entity/English/Geographics/Grammar/EntityNames.rakumod",
    "DSL::Entity::English::Geographics::Actions::Bulgarian::Standard": "lib/DSL/Entity/English/Geographics/Actions/Bulgarian/Standard.rakumod",
    "DSL::Entity::English::Geographics::Actions::WL::Entity": "lib/DSL/Entity/English/Geographics/Actions/WL/Entity.rakumod",
    "DSL::Entity::English::Geographics::Actions::WL::System": "lib/DSL/Entity/English/Geographics/Actions/WL/System.rakumod"
  },
  "depends": [
    "DSL::Shared"
  ],
  "build-depends": [],
  "test-depends": [],
  "resources": [
    "CountryNameToEntityID_EN.csv",
    "CountryAdjectiveToEntityID_EN.csv",
    "RegionNameToEntityID_EN.csv",
    "RegionAdjectiveToEntity_EN.csv"
  ],
  "tags": [
    "city",
    "country",
    "geographic",
    "state",
    "entity",
    "parser",
    "interpreter",
    "ner"
  ],
  "source-url": "https://github.com/antononcube/Raku-DSL-Entity-English-Jobs.git"
}